NDETCStemmer/BestWordSelector.py
NDETCStemmer/CandidateGenerator.py
NDETCStemmer/ListRules.py
NDETCStemmer/ModelDownloader.py
NDETCStemmer/NDETCStemmer.py
NDETCStemmer/NDETCStemmerAbstract.py
NDETCStemmer/RulesGenerator.py
NDETCStemmer/__init__.py
NDETCStemmer/DictFile/compound_word.txt
NDETCStemmer/DictFile/rare_word.txt
NDETCStemmer/DictFile/root_word.txt
NDETCStemmer/DictFile/stopword.txt
NDETCStemmer/Utility/__init__.py
NDETCStemmer/Utility/generator_initiator.py
NDETCStemmer/Utility/normalizer.py
NDETCStemmer/morphology/__init__.py
NDETCStemmer/morphology/infixrule.py
NDETCStemmer/morphology/particlerule.py
NDETCStemmer/morphology/possessivepronounrule.py
NDETCStemmer/morphology/prefix10rule.py
NDETCStemmer/morphology/prefix1rule.py
NDETCStemmer/morphology/prefix20rule.py
NDETCStemmer/morphology/prefix39rule.py
NDETCStemmer/morphology/prefix6rule.py
NDETCStemmer/morphology/reduplicationrule.py
NDETCStemmer/morphology/simulfixrule.py
NDETCStemmer/morphology/suffix2rule_v2.py
NDETCStemmer/morphology/validsuffixprefix.py
NDETCStemmer-1.3.1.dist-info/LICENSE
NDETCStemmer-1.3.1.dist-info/METADATA
NDETCStemmer-1.3.1.dist-info/WHEEL
NDETCStemmer-1.3.1.dist-info/top_level.txt
NDETCStemmer-1.3.1.dist-info/RECORD
